atai_ebook_tool/__init__.py
atai_ebook_tool/cli.py
atai_ebook_tool/parser.py
atai_ebook_tool-0.0.6.dist-info/licenses/LICENSE
atai_ebook_tool-0.0.6.dist-info/METADATA
atai_ebook_tool-0.0.6.dist-info/WHEEL
atai_ebook_tool-0.0.6.dist-info/entry_points.txt
atai_ebook_tool-0.0.6.dist-info/top_level.txt
atai_ebook_tool-0.0.6.dist-info/RECORD
